odoo/addons/spreadsheet_dashboard_disable_share/LICENSE
odoo/addons/spreadsheet_dashboard_disable_share/README.rst
odoo/addons/spreadsheet_dashboard_disable_share/__init__.py
odoo/addons/spreadsheet_dashboard_disable_share/__manifest__.py
odoo/addons/spreadsheet_dashboard_disable_share/images/screen.png
odoo/addons/spreadsheet_dashboard_disable_share/models/__init__.py
odoo/addons/spreadsheet_dashboard_disable_share/models/spreadsheet_dashboard_share.py
odoo/addons/spreadsheet_dashboard_disable_share/readme/CONTRIBUTORS.md
odoo/addons/spreadsheet_dashboard_disable_share/readme/DESCRIPTION.md
odoo/addons/spreadsheet_dashboard_disable_share/readme/USAGE.md
odoo/addons/spreadsheet_dashboard_disable_share/static/description/icon.png
odoo/addons/spreadsheet_dashboard_disable_share/static/description/index.html
odoo/addons/spreadsheet_dashboard_disable_share/static/src/components/dashboard_action.xml
odoo/addons/spreadsheet_dashboard_disable_share/static/src/components/share_button.xml
odoo_addon_spreadsheet_dashboard_disable_share-18.0.1.0.0.dist-info/METADATA
odoo_addon_spreadsheet_dashboard_disable_share-18.0.1.0.0.dist-info/WHEEL
odoo_addon_spreadsheet_dashboard_disable_share-18.0.1.0.0.dist-info/top_level.txt
odoo_addon_spreadsheet_dashboard_disable_share-18.0.1.0.0.dist-info/RECORD
