Metadata-Version: 2.1
Name: odoo-addon-spreadsheet_dashboard_disable_share
Version: 18.0.1.0.0
Requires-Python: >=3.10
Requires-Dist: odoo==18.0.*
Summary: Disable the share feature of dashboards.
Home-page: https://github.com/Mint-system/
License: AGPL-3
Author: Mint System GmbH
Classifier: Programming Language :: Python
Classifier: Framework :: Odoo
Classifier: Framework :: Odoo :: 18.0
Classifier: License :: OSI Approved :: GNU Affero General Public License v3
